gordias/__init__.py
gordias/config.py
gordias/dask_setup.py
gordias/datahandling.py
gordias/metadata.py
gordias/etc/config.yml
gordias/util/__init__.py
gordias/util/cmip_path.py
gordias/util/cube_diffs.py
gordias/util/time_period.py
gordias/util/time_string.py
gordias/util/units.py
gordias-0.3.0.dist-info/LICENSE
gordias-0.3.0.dist-info/METADATA
gordias-0.3.0.dist-info/WHEEL
gordias-0.3.0.dist-info/top_level.txt
gordias-0.3.0.dist-info/RECORD
