Metadata-Version: 2.1
Name: gordias
Version: 0.3.0
Summary: A core project for climate data handling
Author-email: Carolina Nilsson <carolina.nilsson@smhi.se>, Joakim Löw <joakim.low@smhi.se>, Lars Bärring <lars.barring@smhi.se>, Klaus Zimmermann <klaus.zimmermann@smhi.se>
License: Apache-2.0
Project-URL: Homepage, https://git.smhi.se/climix/gordias
Project-URL: Bug Reports, https://git.smhi.se/climix/gordias/issues
Project-URL: Source, https://git.smhi.se/climix/gordias
Classifier: Development Status :: 4 - Beta
Classifier: Environment :: Console
Classifier: Intended Audience :: Science/Research
Classifier: License :: OSI Approved :: Apache Software License
Classifier: Operating System :: OS Independent
Classifier: Programming Language :: Python :: 3.10
Classifier: Programming Language :: Python :: 3.11
Classifier: Programming Language :: Python :: 3.12
Classifier: Programming Language :: Python :: 3.13
Classifier: Topic :: Scientific/Engineering
Classifier: Topic :: Scientific/Engineering :: GIS
Requires-Python: >=3.10
License-File: LICENSE
Requires-Dist: cftime
Requires-Dist: cf-units
Requires-Dist: dask>=2023.1.0
Requires-Dist: dask-jobqueue
Requires-Dist: dask-mpi
Requires-Dist: distributed>=2023.1.0
Requires-Dist: isodate
Requires-Dist: netCDF4
Requires-Dist: numpy<2
Requires-Dist: pandas
Requires-Dist: psutil
Requires-Dist: scitools-iris<4,>=3
